{
    "login_title": "Admin Login",
    "username":"Username",
    "password":"Password",
    "forget_passh":"Forgot Password",
    "forget_passq":"Forgot Password?",
    "login":"Login",
    "forget_inst":"Enter your registered username to reset your password.",
    "signin":"Sign in",
    "reset_password" : "Reset Password",
    "adr_reportHead":"ADR report",
    "unsendHead":"Unsend Report",
    "newsHead":"News Manager",
    "medHead":"Medicine Manager",
    "logout":"Logout",
    "searchPlaceholder":"Search...",
    "med":"Medicine",
    "sympDrop":"Symptom",
    "sevDrop":"Severity Level",
    "more":"More",
    "month":"Month",
    "year":"Year",
    "date":"Date",
    "name":"Name",
    "symp1":"Symptom 1",
    "symp2":"Symptom 2",
    "symp3":"Symptom 3",
    "othSymp" : "Other Symptoms",
    "tel" : "Phone Number",
    "exportTab" : "Export Table",
    "january":"January",
    "february":"February",
    "march":"March",
    "april":"April",
    "may":"May",
    "june":"June",
    "july":"July",
    "august":"August",
    "september":"September",
    "october":"October",
    "november":"November",
    "december":"December",
    "add":"Add",
    "general":"General Information",
    "news":"News",
    "lastUp":"Last update by ",
    "onDate": "on",
    "enable":"Enable",
    "disable":"Disable",
    "rUSure":"Are you sure ",
    "wantToDe":"you want to delete data?",
    "yes":"Yes",
    "no":"No",
    "addNews":"Add News",
    "title":"Title",
    "category":"Category",
    "outLink":"Outside Link",
    "newsDetail":"News Detail",
    "preview":"Preview",
    "previewNewsHead":"Preview News",
    "url":"URL",
    "shortDesc":"Short Description",
    "options":"Options",
    "imgUpTab":"Image upload tabs:",
    "editNews":"Edit News",
    "update":"Update",
    "accManage":"Pharmacist Account Manager",
    "acc":"Account",
    "adminAccAvailability":"*Admin account does not included.",
    "license":"Professional License Number",
    "status":"Status",
    "edit":"Edit",
    "wantToDisable":"you want to disable data?",
    "new":"New",
    "first" :"First",
    "last" :"Last",
    "confirm":"Confirm",
    "manager":"Manager",
    "adrp":"Adverse Drug Monitoring Program",
    "dosageForm":"Dosage form",
    "str":"Strength",
    "ind":"Indication",
    "contraindication":"Contraindication",
    "storage":"Storage Method",
    "par":"Possible Adverse Reaction",
    "upload":"Upload",
    "image":"Image",
    "medGeneralName":"Medicine Generic Name",
    "medMarket":"Medicine Brand Name"
}